{
  "ticker": "ROG",
  "year": 2023,
  "name": "ROG",
  "ir_url": "",
  "data": {
    "Income Statement": {
      "Total net sales": "28,262.9",
      "Net system sales": "21,768.7",
      "Net service and field option sales": "Value not provided",
      "Total cost of sales": "13,770.9",
      "Cost of system sales": "10,406.9",
      "Cost of service and field option sales": "3,364.0",
      "Gross profit": "14,492.0",
      "Research and development (R&D) costs": "4,303.7",
      "Selling, general and administrative (SG&A) costs": "1,165.7",
      "Income from operations": "9,022.6",
      "Interest and other, net": "19.8",
      "Income before income taxes": "9,042.4",
      "Income tax expense": "(1,680.6)",
      "Income after income taxes": "7,361.8",
      "Profit from equity method investments": "209.8",
      "Net income": "7,571.6",
      "Cost of sales": "554.7",
      "Selling, general and administrative costs": "10.7",
      "Revenue from contracts with customers": "Value",
      "Wages and salaries": "5,001.2",
      "Social security expenses": "468.4",
      "Pension and retirement expenses": "395.2",
      "Share-based payments": "172.6",
      "Personnel expenses": "6,037.4",
      "Board of Management": "5.3",
      "Former Board of Management": "1.0",
      "Other employees": "816.8",
      "Total STI bonus expenses": "823.1",
      "Pension plan based on multi-employer union plan": "276.3",
      "Pension plans based on defined contribution and other plans": "118.9",
      "Income tax (expense) / benefit current": "(1,424.1)",
      "Income tax (expense) / benefit deferred": "67.5",
      "Income tax (expense) / benefit Netherlands": "(1,356.6)",
      "Income tax (expense) / benefit Foreign": "(324.0)",
      "Total income tax (expense) / benefit current": "(1,746.8)",
      "Total income tax (expense) / benefit deferred": "66.2",
      "Total income tax (expense) / benefit": "(1,680.6)",
      "Income tax expense based on ASML’s domestic rate": "(2,332.9)",
      "Effects of tax rates in foreign jurisdictions": "26.6",
      "Adjustments in respect of tax incentives": "824.6",
      "Adjustments in respect of prior years’ current taxes": "(211.2)",
      "Adjustments in respect of prior years’ deferred taxes": "93.1",
      "Movements in the liability for unrecognized tax benefits": "(66.8)",
      "Global minimum tax (expense) / benefit": "(2.5)",
      "Change in valuation allowance": "(24.9)",
      "Equity method investments": "(41.6)",
      "Other (credits) and non-tax deductible items": "54.1",
      "Basic net income per ordinary share": "19.25",
      "Diluted net income per ordinary share": "19.24",
      "Total purchases": "3,946.5",
      "Research and development costs": "45.1"
    },
    "Balance Sheet": {
      "Total shareholder equity": "18.5 billion",
      "Balance sheet total": "48.6 billion",
      "Cash and cash equivalents": "12,735.9",
      "Short-term investments": "5.4",
      "Accounts receivable, net": "4,477.5",
      "Finance receivables, net": "317.2",
      "Current tax assets": "283.6",
      "Contract assets": "320.6",
      "Inventories, net": "10,891.5",
      "Other assets": "790.8",
      "Total current assets": "30,737.4",
      "Deferred tax assets": "1,940.7",
      "Loans receivable": "1,456.6",
      "Equity method investments": "903.0",
      "Goodwill": "4,588.6",
      "Other intangible assets, net": "621.3",
      "Property, plant and equipment, net": "6,846.8",
      "Right-of-use assets": "387.2",
      "Total non-current assets": "17,852.2",
      "Total assets": "48,589.6",
      "Accounts payable": "3,500.4",
      "Accrued and other liabilities": "3,146.1",
      "Current tax liabilities": "283.3",
      "Current portion of long-term debt": "1,010.3",
      "Contract liabilities": "5,625.4",
      "Total current liabilities": "20,051.4",
      "Long-term debt": "4,561.8",
      "Deferred and other income tax liabilities": "299.2",
      "Total non-current liabilities": "10,061.4",
      "Total liabilities": "30,112.8",
      "Issued and outstanding shares": "36.0",
      "Share premium": "4,049.0",
      "Treasury shares at cost": "(476.0)",
      "Retained earnings": "14,414.3",
      "Accumulated other comprehensive income": "454.1",
      "Total shareholders’ equity": "18,476.8",
      "Total liabilities and shareholders’ equity": "48,589.6",
      "Lease liabilities": "306.0",
      "Less: non-current portion of accrued and other liabilities": "459.5",
      "Current portion of accrued and other liabilities": "2,686.6",
      "Less: current portion of long-term debt": "1,010.3",
      "Non-current portion of long-term debt": "3,677.3",
      "Liability for unrecognized tax benefits": "-253.1",
      "Deferred tax liabilities": "-46.1",
      "Deferred and other tax assets (liabilities)": "1,641.5",
      "Total liability for unrecognized tax benefits": "-214.0",
      "Balance of accrued interest and penalties": "-39.1",
      "Total liabilities for unrecognized tax benefits including interest and penalties": "-253.1",
      "Confirmed obligations outstanding at the end of the year": "0.3",
      "Derivative financial instruments": "113.6",
      "Money market funds": "6,379.2",
      "Loan receivable": "1,339.4",
      "Property, plant and equipment": "4028.6"
    },
    "Cash Flow Statement": {
      "Net cash provided by (used in) operating activities": "11,166.2",
      "Net cash provided by (used in) investing activities": "(2,609.3)",
      "Net cash provided by (used in) financing activities": "(2,832.1)",
      "Effect of changes in exchange rates on cash": "6.4",
      "Net increase (decrease) in cash and cash equivalents": "5,731.2"
    }
  },
  "tokens_used": 210333
}